bmdrc/BinaryClass.py
bmdrc/LPRClass.py
bmdrc/SimplifiedClass.py
bmdrc/__init__.py
bmdrc/filtering.py
bmdrc/model_fitting.py
bmdrc/output_modules.py
bmdrc/preprocessing.py
bmdrc-1.0.2.dist-info/licenses/LICENSE.txt
bmdrc-1.0.2.dist-info/METADATA
bmdrc-1.0.2.dist-info/WHEEL
bmdrc-1.0.2.dist-info/top_level.txt
bmdrc-1.0.2.dist-info/RECORD
