Metadata-Version: 2.4
Name: bmdrc
Version: 1.0.2
Summary: A package for fitting benchmark dose curves to dichotomous, proportional, and light photomotor response data
Author-email: David Degnan <david.degnan@pnnl.gov>, Lisa Bramer <lisa.bramer@pnnl.gov>, Lisa Truong <lisa.truong@oregonstate.edu>, Robyn Tanguay <robyn.tanguay@oregonstate.edu>, Sara Gosline <sara.gosline@pnnl.gov>, Katrina Waters <katrina.waters@pnnl.gov>
Project-URL: Homepage, https://github.com/PNNL-CompBio/bmdrc
Project-URL: Issues, https://github.com/PNNL-CompBio/bmdrc
Requires-Python: >=3.10
License-File: LICENSE.txt
Requires-Dist: pandas>=2.1.4
Requires-Dist: numpy>=1.26.2
Requires-Dist: scipy>=1.11.4
Requires-Dist: astropy>=6.0.0
Requires-Dist: argparse
Requires-Dist: statsmodels>=0.14.1
Requires-Dist: matplotlib>=3.8.2
Dynamic: license-file
